{"arti":["<b>ah&#xB7;li ne&#xB7;ga&#xB7;ra</b> <i>n</i> orang yg paham benar tt ketatanegaraan;<br><b>ke&#xB7;ah&#xB7;li&#xB7;ne&#xB7;ga&#xB7;ra&#xB7;an</b> <i>n</i> hal atau mengenai orang yg paham benar tt tata negara"],"similar":[{"uri":"ahli","keyword":"ahli"},{"uri":"ahlulbait","keyword":"ahlulbait"},{"uri":"ahlulkitab","keyword":"ahlulkitab"},{"uri":"ahlulkubur","keyword":"ahlulkubur"},{"uri":"ahlunujum","keyword":"ahlunujum"},{"uri":"ahlusuluk","keyword":"ahlusuluk"},{"uri":"ahlusunah","keyword":"ahlusunah"},{"uri":"ah","keyword":"ah"},{"uri":"Ahad","keyword":"Ahad"},{"uri":"ahadiat","keyword":"ahadiat"},{"uri":"ahimsa","keyword":"ahimsa"},{"uri":"ahistoris","keyword":"ahistoris"},{"uri":"ahkam","keyword":"ahkam"},{"uri":"ahmak","keyword":"ahmak"},{"uri":"ahmar","keyword":"ahmar"},{"uri":"aho","keyword":"aho"},{"uri":"ahsan","keyword":"ahsan"},{"uri":"ahwal","keyword":"ahwal"},{"uri":"A","keyword":"A"},{"uri":"a-","keyword":"a-"},{"uri":"ab","keyword":"ab"},{"uri":"ab-","keyword":"ab-"},{"uri":"aba","keyword":"aba"},{"uri":"aba-aba","keyword":"aba-aba"},{"uri":"abad","keyword":"abad"},{"uri":"abadi","keyword":"abadi"},{"uri":"abadiah","keyword":"abadiah"},{"uri":"abadiat","keyword":"abadiat"},{"uri":"abah","keyword":"abah"},{"uri":"abah-abah","keyword":"abah-abah"}]}
