{"arti":["<b>ak&#xB7;ro&#xB7;bat</b> <i>n</i> kemahiran dl melakukan berbagai ketangkasan (spt berjalan di atas tali, naik sepeda beroda satu, menerbangkan pesawat udara);<br>--<b> hukum</b> putusan yg berubah-ubah secara mendadak dl persoalan yg sama dan sering terjadi cabut-mencabut atau ralat-meralat suatu putusan atau kebijakan; --<b> politik</b> <b>1</b> pernyataan yg dikeluarkan hari ini, bisa bertentangan dng pernyataan beberapa saat kemudian; <b>2</b> kader politik yg menyeberang ke partai lain;<br><b>ber&#xB7;ak&#xB7;ro&#xB7;bat</b> <i>v</i> bermain akrobat"],"similar":[{"uri":"/akrobatik","keyword":"akrobatik"},{"uri":"/akrofobia","keyword":"akrofobia"},{"uri":"/akromegali","keyword":"akromegali"},{"uri":"/akrometer","keyword":"akrometer"},{"uri":"/akromion","keyword":"akromion"},{"uri":"/akronim","keyword":"akronim"},{"uri":"/akrab","keyword":"akrab"},{"uri":"/akreditasi","keyword":"akreditasi"},{"uri":"/akriflavina","keyword":"akriflavina"},{"uri":"/akrilat","keyword":"akrilat"},{"uri":"/akrilik","keyword":"akrilik"},{"uri":"/akad","keyword":"akad"},{"uri":"/akademi","keyword":"akademi"},{"uri":"/akademik","keyword":"akademik"},{"uri":"/akademikus","keyword":"akademikus"},{"uri":"/akademis","keyword":"akademis"},{"uri":"/akademisi","keyword":"akademisi"},{"uri":"/akaid","keyword":"akaid"},{"uri":"/akak","keyword":"akak"},{"uri":"/akal","keyword":"akal"},{"uri":"/akan","keyword":"akan"},{"uri":"/akang","keyword":"akang"},{"uri":"/akapela","keyword":"akapela"},{"uri":"/akar","keyword":"akar"},{"uri":"/akas","keyword":"akas"},{"uri":"/akas+kaya","keyword":"akas kaya"},{"uri":"/akasa","keyword":"akasa"},{"uri":"/akasia","keyword":"akasia"},{"uri":"/akatalepsia","keyword":"akatalepsia"},{"uri":"/akbar","keyword":"akbar"}]}
