{"arti":["<b>aku&#xB7;a&#xB7;rel</b> /akuar&#xE9;l/ <i>n</i> gambar yg biasanya dibuat dng cat air transparan"],"similar":[{"uri":"akuaris","keyword":"akuaris"},{"uri":"akuarium","keyword":"akuarium"},{"uri":"Akuarius","keyword":"Akuarius"},{"uri":"akua","keyword":"akua"},{"uri":"akuades","keyword":"akuades"},{"uri":"akuaduk","keyword":"akuaduk"},{"uri":"akuakultur","keyword":"akuakultur"},{"uri":"akualung","keyword":"akualung"},{"uri":"akuamarin","keyword":"akuamarin"},{"uri":"akuan","keyword":"akuan"},{"uri":"akuatik","keyword":"akuatik"},{"uri":"aku","keyword":"aku"},{"uri":"akuifer","keyword":"akuifer"},{"uri":"akuisisi","keyword":"akuisisi"},{"uri":"akuk","keyword":"akuk"},{"uri":"akulturasi","keyword":"akulturasi"},{"uri":"akumulasi","keyword":"akumulasi"},{"uri":"akumulatif","keyword":"akumulatif"},{"uri":"akumulator","keyword":"akumulator"},{"uri":"akun","keyword":"akun"},{"uri":"akuntan","keyword":"akuntan"},{"uri":"akuntansi","keyword":"akuntansi"},{"uri":"akupunktur","keyword":"akupunktur"},{"uri":"akupunkturis","keyword":"akupunkturis"},{"uri":"akur","keyword":"akur"},{"uri":"akurasi","keyword":"akurasi"},{"uri":"akurat","keyword":"akurat"},{"uri":"akusatif","keyword":"akusatif"},{"uri":"akustik","keyword":"akustik"},{"uri":"akustika","keyword":"akustika"}]}
