{"arti":["<b>asum&#xB7;tif</b> <i>a</i> bersifat dugaan (perkiraan)"],"similar":[{"uri":"/asumsi","keyword":"asumsi"},{"uri":"/asu","keyword":"asu"},{"uri":"/asuh","keyword":"asuh"},{"uri":"/asuh-asuh","keyword":"asuh-asuh"},{"uri":"/asung","keyword":"asung"},{"uri":"/asurador","keyword":"asurador"},{"uri":"/asuransi","keyword":"asuransi"},{"uri":"/asusila","keyword":"asusila"},{"uri":"/as","keyword":"as"},{"uri":"/asa","keyword":"asa"},{"uri":"/asabat","keyword":"asabat"},{"uri":"/asabiah","keyword":"asabiah"},{"uri":"/asabiyah","keyword":"asabiyah"},{"uri":"/asad","keyword":"asad"},{"uri":"/asah","keyword":"asah"},{"uri":"/asai","keyword":"asai"},{"uri":"/asak","keyword":"asak"},{"uri":"/asal","keyword":"asal"},{"uri":"/asali","keyword":"asali"},{"uri":"/asam","keyword":"asam"},{"uri":"/asan","keyword":"asan"},{"uri":"/asana","keyword":"asana"},{"uri":"/asap","keyword":"asap"},{"uri":"/asar","keyword":"asar"},{"uri":"/asas","keyword":"asas"},{"uri":"/asasi","keyword":"asasi"},{"uri":"/asbak","keyword":"asbak"},{"uri":"/asbes","keyword":"asbes"},{"uri":"/asbut","keyword":"asbut"},{"uri":"/ase","keyword":"ase"}]}
