{"arti":["<b>Bud&#xB7;dha</b> <i>n</i> <b>1</b> agama yg diajarkan oleh Sidharta Gautama; <b>2</b> orang yg telah mencapai kesempurnaan Buddhisme; <b>3</b> penjelmaan Sidharta Gautama"],"similar":[{"uri":"Buddhis","keyword":"Buddhis"},{"uri":"Buddhisme","keyword":"Buddhisme"},{"uri":"budak","keyword":"budak"},{"uri":"budanco","keyword":"budanco"},{"uri":"budaya","keyword":"budaya"},{"uri":"budayawan","keyword":"budayawan"},{"uri":"bude","keyword":"bude"},{"uri":"budek","keyword":"budek"},{"uri":"budi","keyword":"budi"},{"uri":"budi+daya","keyword":"budi daya"},{"uri":"budian","keyword":"budian"},{"uri":"budiman","keyword":"budiman"},{"uri":"budu","keyword":"budu"},{"uri":"buduk","keyword":"buduk"},{"uri":"budur","keyword":"budur"},{"uri":"bu","keyword":"bu"},{"uri":"bua+tanah","keyword":"bua tanah"},{"uri":"buah","keyword":"buah"},{"uri":"buai","keyword":"buai"},{"uri":"buak","keyword":"buak"},{"uri":"bual","keyword":"bual"},{"uri":"buana","keyword":"buana"},{"uri":"buang","keyword":"buang"},{"uri":"buani","keyword":"buani"},{"uri":"buar","keyword":"buar"},{"uri":"buari","keyword":"buari"},{"uri":"buas","keyword":"buas"},{"uri":"buat","keyword":"buat"},{"uri":"buaya","keyword":"buaya"},{"uri":"buaya-buaya","keyword":"buaya-buaya"}]}
