{"arti":["<b>ca&#xB7;bang</b> <i>n</i> <b>1</b> bagian batang kayu yg tumbuh dr pokok atau dahan (cabang yg besar disebut dahan dan cabang yg kecil disebut ranting): <i>pohon ini tidak banyak -- nya</i>; <b>2</b> galah (tongkat dsb) yg ujungnya berbelah menjadi sudut (Y); canggah; cagak: <i>pohon itu ditopang dng --;</i> <b>3</b> bagian yg terpecah atau terbelah dr pokoknya: --<i> jalan; -- sungai</i>; <b>4</b> satuan usaha (kedai, toko), lembaga, perkumpulan, kantor, dsb yg merupakan bagian dr satuan yg lebih besar; filial: <i>kantor --;</i> <i>perguruan itu mempunyai beratus-ratus -- di seluruh tanah air</i>;<br><b>ber&#xB7;ca&#xB7;bang</b> <i>v</i> <b>1</b> mempunyai cabang (tt batang pohon, tanduk, lembaga, atau kantor): <i>tanduk rusa itu ~; di desa itu ada pohon nyiur yg ~;</i> <b>2</b> terpecah; tidak terpusat pd satu saja (tt hati, pikiran, dsb); mendua; bimbang (tt hati, pikiran): <i>hatinya sudah ~ sehingga sulit dipercaya; </i><b>3</b> berbelah cabang (tt jalan, sungai); bersimpang: <i>jalan (sungai) itu ~ dua</i>; <b>4</b> <i>ki</i> tidak dapat dipercaya (tt perkataan): <i>lidahnya ~;<br></i><b>ber&#xB7;ca&#xB7;bang-ca&#xB7;bang</b> <i>v</i><b> 1</b> banyak tumbuh cabang (tt pohon); <b>2</b> bersimpang-simpang (tt jalan, sungai); <b>3</b> terpecah-pecah atau terbagi-bagi (tt hati, perhatian, pikiran, dsb) thd beberapa masalah; tidak terpusat pd satu masalah (tt pikiran, hati);<br><b>men&#xB7;ca&#xB7;bang</b> <i>v</i><b> 1</b> memecah menjadi beberapa cabang: <i>bank swasta di kota itu ~ di lima lokasi strategis</i>; <i>makhluk manusia mulai ~ dr makhluk manusia pertama</i>; <b>2</b> tumbuh cabangnya; ada cabangnya;<br><b>men&#xB7;ca&#xB7;bang&#xB7;kan</b> <i>v</i> <b>1</b> menempelkan tampang pd batang pohon (supaya menjadi cabang); mengenten; <b>2</b> menjadikan bercabang;<br><b>per&#xB7;ca&#xB7;bang&#xB7;an</b> <i>n</i><b> 1</b> simpang; persimpangan (tt jalan, sungai); <b>2</b> perihal cabang; <b>3</b> tempat tumbuhnya cabang (pd pohon); <b>4</b> <i>Anat</i> pembagian menjadi struktur yg lebih halus: ~<i> ranting pembuluh darah hati</i>;<br><b>mem&#xB7;per&#xB7;ca&#xB7;bang&#xB7;kan</b> <i>v</i> menjadikan bercabang-cabang;<br><b>pen&#xB7;ca&#xB7;bang&#xB7;an</b> <i>n</i> proses, cara, perbuatan mencabangkan: ~<i> bank ke daerah juga salah satu faktor yg mendorong naiknya konsumsi di daerah</i>"],"similar":[{"uri":"caba","keyword":"caba"},{"uri":"cabai","keyword":"cabai"},{"uri":"cabak","keyword":"cabak"},{"uri":"cabar","keyword":"cabar"},{"uri":"cabau","keyword":"cabau"},{"uri":"cabik","keyword":"cabik"},{"uri":"cabir","keyword":"cabir"},{"uri":"cabo","keyword":"cabo"},{"uri":"cabuh","keyword":"cabuh"},{"uri":"cabuk","keyword":"cabuk"},{"uri":"cabul","keyword":"cabul"},{"uri":"cabur","keyword":"cabur"},{"uri":"cabut","keyword":"cabut"},{"uri":"ca","keyword":"ca"},{"uri":"caca","keyword":"caca"},{"uri":"cacah","keyword":"cacah"},{"uri":"cacah+jiwa","keyword":"cacah jiwa"},{"uri":"cacak","keyword":"cacak"},{"uri":"cacap","keyword":"cacap"},{"uri":"cacar","keyword":"cacar"},{"uri":"cacat","keyword":"cacat"},{"uri":"cacau","keyword":"cacau"},{"uri":"cacengklok","keyword":"cacengklok"},{"uri":"caci","keyword":"caci"},{"uri":"caci+maki","keyword":"caci maki"},{"uri":"cacibar","keyword":"cacibar"},{"uri":"cacil","keyword":"cacil"},{"uri":"cacing","keyword":"cacing"},{"uri":"cadai","keyword":"cadai"},{"uri":"cadang","keyword":"cadang"}]}
