{"arti":["<b>cu&#xB7;kil</b> <i>n</i> alat untuk mengorek (melepaskan sesuatu yg ada di dl atau yg melekat); cungkil;<br><b>men&#xB7;cu&#xB7;kil</b> <i>v</i> <b>1</b> mengorek (melepaskan dsb); <b>2</b> memahat (bidang datar) dng cukil; <b>3</b> <i>ki</i> mengutip (karangan dsb);<br><b>cu&#xB7;kil&#xB7;an</b> <i>n</i> <b>1</b> pembuatan gambar atau hiasan pd kayu dng cara memahat, melubangi, mengukir kayu tsb dng pahat; <b>2</b> hasil mencukil; pahatan: ~<i> yg indah itu menghiasi dinding kantornya</i>"],"similar":[{"uri":"/cuki","keyword":"cuki"},{"uri":"/cukimai","keyword":"cukimai"},{"uri":"/cukin","keyword":"cukin"},{"uri":"/cukir","keyword":"cukir"},{"uri":"/cukit","keyword":"cukit"},{"uri":"/cuk","keyword":"cuk"},{"uri":"/cuka","keyword":"cuka"},{"uri":"/cukai","keyword":"cukai"},{"uri":"/cukam","keyword":"cukam"},{"uri":"/cukong","keyword":"cukong"},{"uri":"/cuku","keyword":"cuku"},{"uri":"/cukup","keyword":"cukup"},{"uri":"/cukur","keyword":"cukur"},{"uri":"/cu","keyword":"cu"},{"uri":"/cua","keyword":"cua"},{"uri":"/cuaca","keyword":"cuaca"},{"uri":"/cuai","keyword":"cuai"},{"uri":"/cuak","keyword":"cuak"},{"uri":"/cual","keyword":"cual"},{"uri":"/cuang","keyword":"cuang"},{"uri":"/cuar","keyword":"cuar"},{"uri":"/cuat","keyword":"cuat"},{"uri":"/cuban","keyword":"cuban"},{"uri":"/cubit","keyword":"cubit"},{"uri":"/cublik","keyword":"cublik"},{"uri":"/cubung","keyword":"cubung"},{"uri":"/cuca","keyword":"cuca"},{"uri":"/cucakrawa","keyword":"cucakrawa"},{"uri":"/cuci","keyword":"cuci"},{"uri":"/cuci-maki","keyword":"cuci-maki"}]}
