{"arti":["<b>ek&#xB7;lek&#xB7;tik</b> /&#xE9;kl&#xE9;ktik/ <i>a</i> bersifat memilih yg terbaik dr berbagai sumber (tt orang, gaya, metode)"],"similar":[{"uri":"eklektikus","keyword":"eklektikus"},{"uri":"eklektis","keyword":"eklektis"},{"uri":"eklektisisme","keyword":"eklektisisme"},{"uri":"eklips","keyword":"eklips"},{"uri":"ekliptika","keyword":"ekliptika"},{"uri":"ekliptis","keyword":"ekliptis"},{"uri":"eklosi","keyword":"eklosi"},{"uri":"eka-","keyword":"eka-"},{"uri":"ekabahasa","keyword":"ekabahasa"},{"uri":"ekabahasawan","keyword":"ekabahasawan"},{"uri":"ekad","keyword":"ekad"},{"uri":"ekajati","keyword":"ekajati"},{"uri":"ekakarsa","keyword":"ekakarsa"},{"uri":"ekamatra","keyword":"ekamatra"},{"uri":"ekang","keyword":"ekang"},{"uri":"ekaristi","keyword":"ekaristi"},{"uri":"ekatantri","keyword":"ekatantri"},{"uri":"ekbalium","keyword":"ekbalium"},{"uri":"ekdemik","keyword":"ekdemik"},{"uri":"ekderon","keyword":"ekderon"},{"uri":"ekdisis","keyword":"ekdisis"},{"uri":"ekeh","keyword":"ekeh"},{"uri":"ekimosis","keyword":"ekimosis"},{"uri":"ekiofit","keyword":"ekiofit"},{"uri":"ekofisiologi","keyword":"ekofisiologi"},{"uri":"ekofraksia","keyword":"ekofraksia"},{"uri":"ekografi","keyword":"ekografi"},{"uri":"ekogrup","keyword":"ekogrup"},{"uri":"ekoklimat","keyword":"ekoklimat"},{"uri":"ekoklimatologi","keyword":"ekoklimatologi"}]}
