{"arti":["<b>ja&#xB7;mah</b> <i>v,</i> <b>men&#xB7;ja&#xB7;mah 1</b> <i>v</i> menyentuh dng jari; meraba; memegang: <i>ia ~ tubuh orang itu;</i> <b>2</b> <i>ki</i> meniduri; menodai: <i>pemuda itu telah ~ gadis kampung itu;<br></i><b>ter&#xB7;ja&#xB7;mah</b> <i>v</i> <b>1</b> sudah dijamah; <b>2</b> dijamah tanpa disengaja; tersentuh; <b>3</b> dimasuki; dikenal (tt daerah, hutan, dsb): <i>hutan itu belum ~ oleh manusia;<br></i><b>ja&#xB7;mah&#xB7;an</b> <i>n</i> hasil menjamah; sentuhan (dng jari); rabaan; pegangan: ~<i> tangannya lembut mengesankan;<br></i><b>ja&#xB7;mah-ja&#xB7;mah&#xB7;an</b> <i>n</i> hamba perempuan yg dipergundik;<br><b>pen&#xB7;ja&#xB7;mah</b> <i>n</i> orang yg menjamah;<br><b>pen&#xB7;ja&#xB7;mah&#xB7;an</b> <i>n</i> <b>1</b> proses, cara, perbuatan menjamah; <b>2</b> pegangan; pekerjaan (sesuatu yg dikerjakan)"],"similar":[{"uri":"/jamaah","keyword":"jamaah"},{"uri":"/jamadat","keyword":"jamadat"},{"uri":"/jamak","keyword":"jamak"},{"uri":"/jamal","keyword":"jamal"},{"uri":"/jaman","keyword":"jaman"},{"uri":"/jamang","keyword":"jamang"},{"uri":"/jam","keyword":"jam"},{"uri":"/jambak","keyword":"jambak"},{"uri":"/jambal","keyword":"jambal"},{"uri":"/jamban","keyword":"jamban"},{"uri":"/jambang","keyword":"jambang"},{"uri":"/jambar","keyword":"jambar"},{"uri":"/jambat","keyword":"jambat"},{"uri":"/jambe","keyword":"jambe"},{"uri":"/jambiah","keyword":"jambiah"},{"uri":"/jambian","keyword":"jambian"},{"uri":"/jamblang","keyword":"jamblang"},{"uri":"/jambon","keyword":"jambon"},{"uri":"/jambore","keyword":"jambore"},{"uri":"/jambret","keyword":"jambret"},{"uri":"/jambu","keyword":"jambu"},{"uri":"/jambul","keyword":"jambul"},{"uri":"/jambulan","keyword":"jambulan"},{"uri":"/jambur","keyword":"jambur"},{"uri":"/jamhur","keyword":"jamhur"},{"uri":"/jamiah","keyword":"jamiah"},{"uri":"/jamiatul+hujaj","keyword":"jamiatul hujaj"},{"uri":"/jamik","keyword":"jamik"},{"uri":"/jamil","keyword":"jamil"},{"uri":"/jamin","keyword":"jamin"}]}
