{"arti":["<b><sup>1</sup>ju&#xB7;ri</b> <i>n</i> <b>1</b> orang (panitia) yg menilai dan memutuskan kalah atau menang (dl perlombaan, sayembara, dsb): <i>dia ditunjuk menjadi anggota -- dl perlombaan pidato itu</i>; <b>2</b> orang yg menilai salah atau benar di pengadilan (di beberapa negeri Barat);<br><b>pen&#xB7;ju&#xB7;ri&#xB7;an</b> <i>n</i> proses, cara, perbuatan menilai dan memutuskan (dl perlombaan, pertandingan, dsb)","<b><sup>2</sup>ju&#xB7;ri ? jori</b>"],"similar":[{"uri":"juriat","keyword":"juriat"},{"uri":"jurik","keyword":"jurik"},{"uri":"juring","keyword":"juring"},{"uri":"juris","keyword":"juris"},{"uri":"jurit","keyword":"jurit"},{"uri":"jura","keyword":"jura"},{"uri":"juragan","keyword":"juragan"},{"uri":"jurah","keyword":"jurah"},{"uri":"jurai","keyword":"jurai"},{"uri":"juran","keyword":"juran"},{"uri":"jurang","keyword":"jurang"},{"uri":"jurnal","keyword":"jurnal"},{"uri":"jurnalis","keyword":"jurnalis"},{"uri":"jurnalisme","keyword":"jurnalisme"},{"uri":"jurnalistik","keyword":"jurnalistik"},{"uri":"juru","keyword":"juru"},{"uri":"juru+bicara","keyword":"juru bicara"},{"uri":"juruh","keyword":"juruh"},{"uri":"jurung","keyword":"jurung"},{"uri":"jurus","keyword":"jurus"},{"uri":"jua","keyword":"jua"},{"uri":"juadah","keyword":"juadah"},{"uri":"juak","keyword":"juak"},{"uri":"jual","keyword":"jual"},{"uri":"jual+beli","keyword":"jual beli"},{"uri":"juandang","keyword":"juandang"},{"uri":"juang","keyword":"juang"},{"uri":"juar","keyword":"juar"},{"uri":"juara","keyword":"juara"},{"uri":"jubah","keyword":"jubah"}]}
