{"arti":["<b>kam&#xB7;ka&#xB7;ma</b> ? <b>kurkuma</b>"],"similar":[{"uri":"kamka","keyword":"kamka"},{"uri":"kam","keyword":"kam"},{"uri":"kama","keyword":"kama"},{"uri":"Kamajaya","keyword":"Kamajaya"},{"uri":"kamal","keyword":"kamal"},{"uri":"kamalir","keyword":"kamalir"},{"uri":"kamantuhu","keyword":"kamantuhu"},{"uri":"kamar","keyword":"kamar"},{"uri":"kamarban","keyword":"kamarban"},{"uri":"kamariah","keyword":"kamariah"},{"uri":"kamas","keyword":"kamas"},{"uri":"kamat","keyword":"kamat"},{"uri":"kamba","keyword":"kamba"},{"uri":"kamban","keyword":"kamban"},{"uri":"kambang","keyword":"kambang"},{"uri":"kambar","keyword":"kambar"},{"uri":"kambau","keyword":"kambau"},{"uri":"kambeh","keyword":"kambeh"},{"uri":"kambeli","keyword":"kambeli"},{"uri":"kamber","keyword":"kamber"},{"uri":"kambi","keyword":"kambi"},{"uri":"kambing","keyword":"kambing"},{"uri":"kambing+hitam","keyword":"kambing hitam"},{"uri":"kambium","keyword":"kambium"},{"uri":"kambrat","keyword":"kambrat"},{"uri":"kambrik","keyword":"kambrik"},{"uri":"kambrium","keyword":"kambrium"},{"uri":"kambuh","keyword":"kambuh"},{"uri":"kambus","keyword":"kambus"},{"uri":"kambut","keyword":"kambut"}]}
