{"arti":["<b>ke&#xB7;ra&#xB7;bat</b> <i>n</i> <b>1</b> yg dekat (pertalian keluarga); sedarah sedaging: <i>masih -- dng engkau;</i> <b>2</b> keluarga; sanak saudara: <i>kaum --;</i> <b>3</b> keturunan dr induk yg sama yg dihasilkan dr gamet yg berbeda;<br>--<b> angkat</b> <i>Antr</i> kerabat yg berdasarkan adat atau hukum tt adopsi yg berlaku dl suatu masyarakat; --<b> kawin</b> <i>Antr</i> kerabat berdasarkan ikatan perkawinan; --<b> kerja</b> sekelompok petugas sepekerjaan yg tergabung sementara untuk melaksanakan tugas yg sama; --<b> sebagian</b> <i>Ikn</i> keturunan yg hanya mempunyai satu induk sama; --<b> sedarah</b> <i>Antr</i> kerabat berdasarkan hubungan darah;<br><b>ber&#xB7;ke&#xB7;ra&#xB7;bat</b> <i>v</i> mempunyai hubungan keluarga: <i>ia masih ~ denganku;<br></i><b>ke&#xB7;ke&#xB7;ra&#xB7;bat&#xB7;an</b> <i>n</i> <b>1</b> perihal berkerabat; <b>2</b> <i>Ling</i> hubungan antara dua bahasa atau lebih yg diturunkan dr sumber yg sama"],"similar":[{"uri":"kerabang","keyword":"kerabang"},{"uri":"kerabik","keyword":"kerabik"},{"uri":"kerabu","keyword":"kerabu"},{"uri":"kera","keyword":"kera"},{"uri":"keracak","keyword":"keracak"},{"uri":"keracap","keyword":"keracap"},{"uri":"keraeng","keyword":"keraeng"},{"uri":"kerah","keyword":"kerah"},{"uri":"kerahi","keyword":"kerahi"},{"uri":"kerai","keyword":"kerai"},{"uri":"kerajang","keyword":"kerajang"},{"uri":"kerajat","keyword":"kerajat"},{"uri":"kerak","keyword":"kerak"},{"uri":"kerakah","keyword":"kerakah"},{"uri":"kerakal","keyword":"kerakal"},{"uri":"kerakap","keyword":"kerakap"},{"uri":"kerakeling","keyword":"kerakeling"},{"uri":"keram","keyword":"keram"},{"uri":"kerama","keyword":"kerama"},{"uri":"keraman","keyword":"keraman"},{"uri":"keramas","keyword":"keramas"},{"uri":"keramat","keyword":"keramat"},{"uri":"keramba","keyword":"keramba"},{"uri":"kerambil","keyword":"kerambil"},{"uri":"kerambit","keyword":"kerambit"},{"uri":"keramboja","keyword":"keramboja"},{"uri":"keramik","keyword":"keramik"},{"uri":"keramikus","keyword":"keramikus"},{"uri":"kerampagi","keyword":"kerampagi"},{"uri":"kerampang","keyword":"kerampang"}]}
