{"arti":["<b><sup>1</sup>kre&#xB7;dit</b> /kr&#xE9;dit/ <i>n</i> <b>1</b> cara menjual barang dng pembayaran secara tidak tunai (pembayaran ditangguhkan atau diangsur); <b>2</b> pinjaman uang dng pembayaran pengembalian secara mengangsur; <b>3</b> penambahan saldo rekening, sisa utang, modal, dan pendataan bagi penabung; <b>4</b> pinjaman sampai batas jumlah tertentu yg diizinkan oleh bank atau badan lain; <b>5</b> sisi kanan neraca (di Indonesia);<br>--<b> griya sembada</b> kredit untuk membangun rumah sewa; --<b> investasi</b> kredit yg digunakan untuk membiayai pembelian barang atau modal yg bersifat tetap (tidak habis dl satu proses produksi, spt tanah dan mesin-mesin); --<b> jangka menengah</b> kredit yg berjangka (waktu) satu tahun sampai tiga tahun; --<b> jangka panjang</b> kredit yg berjangka (waktu) lebih dr tiga tahun; --<b> jangka pendek</b> kredit yg berjangka (waktu) maksimum satu tahun; --<b> komersial</b> kredit jangka pendek dng suku bunga tinggi; --<b> konsumtif</b> kredit untuk pembelian barang yg langsung memenuhi keperluan hidup kita, msl rumah; --<b> lunak</b> kredit dng bunga rendah dan waktu pengembaliannya tidak mengikat (longgar); --<b> penyimpanan</b> kredit yg digunakan untuk keperluan penyimpanan hasil pertanian; --<b> slip</b> kredit berupa kupon dng nilai pembayaran untuk penggunaan jasa angkutan; --<b> swagriya</b> kredit pembangunan rumah; --<b> tata niaga</b> kredit yg diperuntukkan bagi pembiayaan tata niaga hasil pertanian; --<b> terbimbing</b> kredit yg penggunaannya diawasi dan dibimbing oleh pihak pemberi kredit (msl kredit Bimas); --<b> upakara</b> kredit untuk perbaikan atau perluasan rumah tinggal yg sifatnya akan menambah nilai rumah;<br><b>meng&#xB7;kre&#xB7;dit</b> <i>v</i> meminjam uang, membeli barang, dsb yg dikembalikan atau dibayar secara angsuran: <i>dia ~ rumah selama lima tahun</i>;<br><b>meng&#xB7;kre&#xB7;dit&#xB7;kan</b> <i>v</i> <b>1</b> menjual barang dng pembayaran secara mengangsur; <b>2</b> meminjamkan uang dng mengembalikan secara mengangsur; <b>3</b> <i>cak</i> meminjamkan uang dng tanggungan barang;<br><b>kre&#xB7;dit&#xB7;an</b> <i>n</i> <b>1</b> pinjaman uang; kredit; <b>2</b> cara pembayaran dng mengangsur: <i>televisi itu dibelinya dng ~;<br></i><b>per&#xB7;kre&#xB7;dit&#xB7;an</b> <i>n</i> segala urusan yg berhubungan dng kredit-mengkreditkan; perihal kredit;<br><b>peng&#xB7;kre&#xB7;dit</b> <i>n</i> kreditor;<br><b>peng&#xB7;kre&#xB7;dit&#xB7;an</b> <i>n</i> proses, cara, perbuatan mengkreditkan","<b><sup>2</sup>kre&#xB7;dit</b> /kr&#xE9;dit/ <i>n</i> <b>1</b> harga atau nilai untuk suatu tindakan (yg baik): <i>pengabdian masyarakat merupakan -- tersendiri bagi seorang dosen;</i> <b>2</b> nilai suatu mata pelajaran dl satu semester: <i>mata pelajaran itu bernilai dua --;<br></i>--<b> sementara</b> <i>Dik</i> satuan beban perkuliahan dl satu semester yg diberikan pd mata kuliah tertentu untuk dosen dan untuk mahasiswa yg mengambil mata kuliah tsb"],"similar":[{"uri":"kredibilitas","keyword":"kredibilitas"},{"uri":"kreditabel","keyword":"kreditabel"},{"uri":"kreditor","keyword":"kreditor"},{"uri":"kredo","keyword":"kredo"},{"uri":"kreasi","keyword":"kreasi"},{"uri":"kreatif","keyword":"kreatif"},{"uri":"kreativitas","keyword":"kreativitas"},{"uri":"kreator","keyword":"kreator"},{"uri":"krebo","keyword":"krebo"},{"uri":"krecek","keyword":"krecek"},{"uri":"krem","keyword":"krem"},{"uri":"kremasi","keyword":"kremasi"},{"uri":"krematori","keyword":"krematori"},{"uri":"krematorium","keyword":"krematorium"},{"uri":"kreol","keyword":"kreol"},{"uri":"kreolin","keyword":"kreolin"},{"uri":"kreolisasi","keyword":"kreolisasi"},{"uri":"kreosol","keyword":"kreosol"},{"uri":"kreseh-peseh","keyword":"kreseh-peseh"},{"uri":"kresendo","keyword":"kresendo"},{"uri":"kresol","keyword":"kresol"},{"uri":"kretin","keyword":"kretin"},{"uri":"krah","keyword":"krah"},{"uri":"krai","keyword":"krai"},{"uri":"krail","keyword":"krail"},{"uri":"krakal","keyword":"krakal"},{"uri":"kram","keyword":"kram"},{"uri":"krama","keyword":"krama"},{"uri":"kran","keyword":"kran"},{"uri":"kranapaksa","keyword":"kranapaksa"}]}
