{"arti":["<b>la&#xB7;bil</b> <i>a</i> <b>1</b> goyah; tidak mantap; tidak kokoh (tt bangunan, pendirian, dsb); <b>2</b> goyang; tidak tenang (tt kendaraan, kapal, pesawat terbang, dsb); <b>3</b> tidak tetap; mudah berubah-ubah; naik turun (tt harga barang, nilai uang, dsb); <b>4</b> tidak stabil; cenderung berubah; <b>5</b> <i>Fis</i> tidak seimbang dan mudah berubah;<br><b>ke&#xB7;la&#xB7;bil&#xB7;an</b> <i>n</i> perihal labil"],"similar":[{"uri":"labi-labi","keyword":"labi-labi"},{"uri":"labial","keyword":"labial"},{"uri":"labialisasi","keyword":"labialisasi"},{"uri":"labiodental","keyword":"labiodental"},{"uri":"labiovelar","keyword":"labiovelar"},{"uri":"labirin","keyword":"labirin"},{"uri":"labium","keyword":"labium"},{"uri":"lab","keyword":"lab"},{"uri":"laba","keyword":"laba"},{"uri":"laba-laba","keyword":"laba-laba"},{"uri":"labah-labah","keyword":"labah-labah"},{"uri":"labak","keyword":"labak"},{"uri":"labang","keyword":"labang"},{"uri":"labas","keyword":"labas"},{"uri":"label","keyword":"label"},{"uri":"labelum","keyword":"labelum"},{"uri":"laberang","keyword":"laberang"},{"uri":"laboran","keyword":"laboran"},{"uri":"laboratoris","keyword":"laboratoris"},{"uri":"laboratorium","keyword":"laboratorium"},{"uri":"labrak","keyword":"labrak"},{"uri":"labrakan","keyword":"labrakan"},{"uri":"labrang","keyword":"labrang"},{"uri":"labres","keyword":"labres"},{"uri":"labrum","keyword":"labrum"},{"uri":"labu","keyword":"labu"},{"uri":"labuda","keyword":"labuda"},{"uri":"labuh","keyword":"labuh"},{"uri":"labun","keyword":"labun"},{"uri":"labur","keyword":"labur"}]}
