{"arti":["<b>le&#xB7;bai</b> <i>n</i> pegawai masjid atau orang yg mengurus suatu pekerjaan yg bertalian dng agama Islam di dusun (kampung);<br>--<b> malang</b> <i>ki</i> orang yg selalu bernasib sial; --<b> penghulu</b> penghulu agama di distrik"],"similar":[{"uri":"/lebah","keyword":"lebah"},{"uri":"/lebak","keyword":"lebak"},{"uri":"/lebam","keyword":"lebam"},{"uri":"/leban","keyword":"leban"},{"uri":"/lebang","keyword":"lebang"},{"uri":"/lebap","keyword":"lebap"},{"uri":"/lebar","keyword":"lebar"},{"uri":"/Lebaran","keyword":"Lebaran"},{"uri":"/lebas","keyword":"lebas"},{"uri":"/lebat","keyword":"lebat"},{"uri":"/leber","keyword":"leber"},{"uri":"/lebih","keyword":"lebih"},{"uri":"/lebuh","keyword":"lebuh"},{"uri":"/lebuk","keyword":"lebuk"},{"uri":"/lebum","keyword":"lebum"},{"uri":"/lebun","keyword":"lebun"},{"uri":"/lebung","keyword":"lebung"},{"uri":"/lebur","keyword":"lebur"},{"uri":"/leak","keyword":"leak"},{"uri":"/lecah","keyword":"lecah"},{"uri":"/lecak","keyword":"lecak"},{"uri":"/lecap","keyword":"lecap"},{"uri":"/lecat","keyword":"lecat"},{"uri":"/leceh","keyword":"leceh"},{"uri":"/lecek","keyword":"lecek"},{"uri":"/lecer","keyword":"lecer"},{"uri":"/lecet","keyword":"lecet"},{"uri":"/leci","keyword":"leci"},{"uri":"/lecit","keyword":"lecit"},{"uri":"/leco","keyword":"leco"}]}
