{"arti":["<b>ma&#xB7;mik</b> <i>a</i> berubah rasanya menjadi kurang sedap (tt makanan, buah-buahan, dsb)"],"similar":[{"uri":"mami","keyword":"mami"},{"uri":"mam","keyword":"mam"},{"uri":"mama","keyword":"mama"},{"uri":"mamah","keyword":"mamah"},{"uri":"mamai","keyword":"mamai"},{"uri":"mamak","keyword":"mamak"},{"uri":"mamalia","keyword":"mamalia"},{"uri":"maman","keyword":"maman"},{"uri":"mamanah","keyword":"mamanah"},{"uri":"mamanda","keyword":"mamanda"},{"uri":"mamang","keyword":"mamang"},{"uri":"mamano","keyword":"mamano"},{"uri":"mamar","keyword":"mamar"},{"uri":"mamat","keyword":"mamat"},{"uri":"mambang","keyword":"mambang"},{"uri":"mambek","keyword":"mambek"},{"uri":"mambo","keyword":"mambo"},{"uri":"mambruk","keyword":"mambruk"},{"uri":"mambu","keyword":"mambu"},{"uri":"mambung","keyword":"mambung"},{"uri":"mamduhah","keyword":"mamduhah"},{"uri":"mamlakat","keyword":"mamlakat"},{"uri":"mamografi","keyword":"mamografi"},{"uri":"mampai","keyword":"mampai"},{"uri":"mampat","keyword":"mampat"},{"uri":"mampir","keyword":"mampir"},{"uri":"mampu","keyword":"mampu"},{"uri":"mampung","keyword":"mampung"},{"uri":"mampus","keyword":"mampus"},{"uri":"mamut","keyword":"mamut"}]}
