{"arti":["<b><sup>1</sup>me&#xB7;gat</b> <i>n</i> gelar bangsawan Melayu (ayahnya orang kebanyakan, ibunya keturunan raja)","<b><sup>2</sup>me&#xB7;gat</b> <i>a</i> masyhur; terkenal: <i>sultan dan raja pd masa itu sangat -- dan megah</i>","<b><sup>3</sup>me&#xB7;gat</b> <i>a</i> berpusing (pd gasing); mejam; ligat"],"similar":[{"uri":"megaton","keyword":"megaton"},{"uri":"megatren","keyword":"megatren"},{"uri":"megatruh","keyword":"megatruh"},{"uri":"mega","keyword":"mega"},{"uri":"mega-","keyword":"mega-"},{"uri":"megafon","keyword":"megafon"},{"uri":"megah","keyword":"megah"},{"uri":"megak","keyword":"megak"},{"uri":"megakredit","keyword":"megakredit"},{"uri":"megal-megol","keyword":"megal-megol"},{"uri":"megalit","keyword":"megalit"},{"uri":"Megalitikum","keyword":"Megalitikum"},{"uri":"megalomania","keyword":"megalomania"},{"uri":"megalomaniak","keyword":"megalomaniak"},{"uri":"megalopolis","keyword":"megalopolis"},{"uri":"megalosit","keyword":"megalosit"},{"uri":"megamerger","keyword":"megamerger"},{"uri":"megan","keyword":"megan"},{"uri":"megaohm","keyword":"megaohm"},{"uri":"megap-megap","keyword":"megap-megap"},{"uri":"megapolis","keyword":"megapolis"},{"uri":"megaproyek","keyword":"megaproyek"},{"uri":"megar","keyword":"megar"},{"uri":"megaspora","keyword":"megaspora"},{"uri":"megasporangium","keyword":"megasporangium"},{"uri":"megasporofil","keyword":"megasporofil"},{"uri":"megawatt","keyword":"megawatt"},{"uri":"meger","keyword":"meger"},{"uri":"megrek-megrek","keyword":"megrek-megrek"},{"uri":"meander","keyword":"meander"}]}
