{"arti":["<b>ning&#xB7;rat</b> <i>n</i> golongan orang-orang mulia; bangsawan; borjuis;<br><b>me&#xB7;ning&#xB7;rat&#xB7;kan</b> <i>v</i> memuliakan, meninggikan derajat bangsawan; menjadi anggota bangsawan;<br><b>ke&#xB7;ning&#xB7;rat-ning&#xB7;rat&#xB7;an</b> <i>v</i> (bertindak, berlaku) spt kaum ningrat (biasanya dianggap jelek, negatif, dsb): <i>hidup ~</i>"],"similar":[{"uri":"ning","keyword":"ning"},{"uri":"ningnong","keyword":"ningnong"},{"uri":"ninabobo","keyword":"ninabobo"},{"uri":"nini","keyword":"nini"},{"uri":"ninik","keyword":"ninik"},{"uri":"ninitowok","keyword":"ninitowok"},{"uri":"ninitowong","keyword":"ninitowong"},{"uri":"ni","keyword":"ni"},{"uri":"nia","keyword":"nia"},{"uri":"niaga","keyword":"niaga"},{"uri":"niagawan","keyword":"niagawan"},{"uri":"nian","keyword":"nian"},{"uri":"niasin","keyword":"niasin"},{"uri":"niat","keyword":"niat"},{"uri":"nibung","keyword":"nibung"},{"uri":"nidasi","keyword":"nidasi"},{"uri":"nidera","keyword":"nidera"},{"uri":"nidikola","keyword":"nidikola"},{"uri":"nidulus","keyword":"nidulus"},{"uri":"nifak","keyword":"nifak"},{"uri":"nifas","keyword":"nifas"},{"uri":"nih","keyword":"nih"},{"uri":"nihil","keyword":"nihil"},{"uri":"nihilis","keyword":"nihilis"},{"uri":"nihilisme","keyword":"nihilisme"},{"uri":"nijas","keyword":"nijas"},{"uri":"nik","keyword":"nik"},{"uri":"nikah","keyword":"nikah"},{"uri":"nikel","keyword":"nikel"},{"uri":"nikmat","keyword":"nikmat"}]}
