{"arti":["<b>pa&#xB7;du</b> <b>1</b> <i>a</i> padat; pejal; kimpal (tt logam dsb): <i>batu bara yg --;</i> <b>2</b> <i>v</i> sudah bercampur dan sudah menjadi satu benar; <i>bersatu -- ,</i> bersatu benar-benar (seia sekata, sehidup semati); <b>3</b> <i>a ki</i> utuh dan kuat; kompak: <i>rakyat dan TNI merupakan kesatuan yg --;<br></i>--<b> mancung</b> perhubungan (pertemuan) dua buah sisi yg membentuk (merupakan) sudut (sanding); --<b> padan</b> memadukan dan memadankan warna pakaian dsb supaya tampak serasi;<br><b>ber&#xB7;pa&#xB7;du</b> <i>v</i> <b>1</b> menjadi satu benar; luluh dan bercampur menjadi satu: <i>angin laut dan desir ombak ~ suara</i>; <b>2</b> beku dan menjadi keras (tt darah, air gula, dsb): <i>darahnya ~;</i> <b>3</b> kukuh krn telah disatukan: <i>partai-partai politik ~ dl satu asas, Pancasila</i>; <b>4</b> bercampur (dng): <i>suka dan duka ~ mengharu hati</i>;<br><b>ber&#xB7;pa&#xB7;du-pa&#xB7;du</b> <i>v</i> <b>1</b> bersatu benar-benar; <b>2</b> menyesuaikan pendapat; bermusyawarah;<br><b>me&#xB7;ma&#xB7;du</b> <i>v</i> <b>1</b> melebur (emas); melebur dan mencampurkan menjadi satu (tt logam); mengaduk (meremas, mengocok, dsb) supaya bercampur (tt tepung dng mentega, semen dng pasir, dsb): ~<i> perak dng tembaga; ~ adonan tepung terigu dng telur</i>; <b>2</b> menyatukan; menggabungkan (bunyi, perkataan, kalimat, dsb) menjadi satu; mengumpulkan (modal): <i>memperhebat usaha ~ modal nasional</i>; <b>3</b> menjadikan padu (padat, kukuh, teguh); mengikat menjadi satu: <i>kedua remaja itu sudah ~ janji</i>; <b>4</b> membandingkan (satu dng lain); menyesuaikan (untuk mengetahui cocok tidaknya); menyerasikan: <i>seorang wanita harus dapat ~ kebaya dng kain dan selendang yg dipakainya</i>;<br>~<b> hati (dng)</b> menyatukan hati (dng); berunding (dng); ~<b> janji</b> mengikat janji; ~<b> kasih</b> berkasih-kasihan; ~<b> pakaian</b> menyesuaikan pakaian (dng badan); ~<b> pendapat</b> menyesuaikan pendapat; membulatkan pendapat; menyatukan pendapat;<br><b>me&#xB7;ma&#xB7;du&#xB7;kan</b> <i>v</i> <b>1</b> membuat supaya padu; menjadikan padu; <b>2</b> menyesuaikan;<br><b>mem&#xB7;per&#xB7;pa&#xB7;du&#xB7;kan</b> <i>v</i> menjadikan berpadu;<br><b>pa&#xB7;du&#xB7;an</b> <i>n</i> yg sudah dipadu (disatukan, dijadikan satu, dsb); hasil memadu;<br>~<b> suara</b> nyanyian bersama (biasanya terdiri atas suara sopran, alto, tenor, dan bariton);<br><b>ke&#xB7;pa&#xB7;du&#xB7;an</b> <i>n</i> keadaan padu; kesatuan (pikiran dsb); kebulatan (pendapat dsb);<br><b>ter&#xB7;pa&#xB7;du</b> <i>v</i> sudah dipadu (disatukan, dilebur menjadi satu, dsb);<br><b>ke&#xB7;ter&#xB7;pa&#xB7;du&#xB7;an</b> <i>n</i> perihal terpadu;<br><b>per&#xB7;pa&#xB7;du&#xB7;an</b> <i>n</i> <b>1</b> perihal (keadaan) berpadu; <b>2</b> persesuaian;<br><b>pe&#xB7;ma&#xB7;du</b> <i>n</i> alat untuk memadukan;<br><b>pe&#xB7;ma&#xB7;du&#xB7;an</b> <i>n</i> proses, cara, perbuatan memadu; penyatuan"],"similar":[{"uri":"padudan","keyword":"padudan"},{"uri":"paduk","keyword":"paduk"},{"uri":"paduka","keyword":"paduka"},{"uri":"paduraksa","keyword":"paduraksa"},{"uri":"padusi","keyword":"padusi"},{"uri":"pada","keyword":"pada"},{"uri":"padah","keyword":"padah"},{"uri":"padahal","keyword":"padahal"},{"uri":"padak","keyword":"padak"},{"uri":"padam","keyword":"padam"},{"uri":"padan","keyword":"padan"},{"uri":"padang","keyword":"padang"},{"uri":"padas","keyword":"padas"},{"uri":"padasan","keyword":"padasan"},{"uri":"padat","keyword":"padat"},{"uri":"padepokan","keyword":"padepokan"},{"uri":"padi","keyword":"padi"},{"uri":"padma","keyword":"padma"},{"uri":"padmasana","keyword":"padmasana"},{"uri":"padmi","keyword":"padmi"},{"uri":"padri","keyword":"padri"},{"uri":"pa","keyword":"pa"},{"uri":"pabean","keyword":"pabean"},{"uri":"pabrik","keyword":"pabrik"},{"uri":"pabrikan","keyword":"pabrikan"},{"uri":"pabrikasi","keyword":"pabrikasi"},{"uri":"pacai","keyword":"pacai"},{"uri":"pacak","keyword":"pacak"},{"uri":"pacal","keyword":"pacal"},{"uri":"pacangan","keyword":"pacangan"}]}
