{"arti":["<b>pi&#xB7;cah</b> ? <b>1pica</b>"],"similar":[{"uri":"pica","keyword":"pica"},{"uri":"pici","keyword":"pici"},{"uri":"picik","keyword":"picik"},{"uri":"picing","keyword":"picing"},{"uri":"picis","keyword":"picis"},{"uri":"picit","keyword":"picit"},{"uri":"pico","keyword":"pico"},{"uri":"picu","keyword":"picu"},{"uri":"picung","keyword":"picung"},{"uri":"pi","keyword":"pi"},{"uri":"piadah","keyword":"piadah"},{"uri":"piagam","keyword":"piagam"},{"uri":"piah","keyword":"piah"},{"uri":"piak","keyword":"piak"},{"uri":"pial","keyword":"pial"},{"uri":"piala","keyword":"piala"},{"uri":"pialang","keyword":"pialang"},{"uri":"pialing","keyword":"pialing"},{"uri":"pialu","keyword":"pialu"},{"uri":"piama","keyword":"piama"},{"uri":"piang","keyword":"piang"},{"uri":"pianggang","keyword":"pianggang"},{"uri":"pianggu","keyword":"pianggu"},{"uri":"pianika","keyword":"pianika"},{"uri":"pianis","keyword":"pianis"},{"uri":"piano","keyword":"piano"},{"uri":"pianola","keyword":"pianola"},{"uri":"piantan","keyword":"piantan"},{"uri":"piara","keyword":"piara"},{"uri":"piarit","keyword":"piarit"}]}
