{"arti":["<b>pu&#xB7;jang&#xB7;ga</b> <i>n</i> <b>1</b> pengarang hasil-hasil sastra, baik puisi maupun prosa; <b>2</b> ahli pikir; ahli sastra; bujangga;<br>--<b> Baru</b> angkatan dl kesusastraan Indonesia yg muncul sekitar tahun 1930-an dng ditandai oleh semangat kebangsaan dan semangat mengejar kemajuan, dipengaruhi oleh aliran romantik dan individualisme; --<b> gereja</b> orang kudus (baik pria maupun wanita segala zaman, yg dihargai secara khusus krn ajaran yg dikemukakan benar, mendalam, dan sangat bijaksana);<br><b>ke&#xB7;pu&#xB7;jang&#xB7;ga&#xB7;an</b> <i>n</i> perihal (yg bersifat, berciri) pujangga; segala sesuatu mengenai pujangga (karang-mengarang susastra)"],"similar":[{"uri":"puja","keyword":"puja"},{"uri":"puji","keyword":"puji"},{"uri":"pujuk","keyword":"pujuk"},{"uri":"pujur","keyword":"pujur"},{"uri":"pujut","keyword":"pujut"},{"uri":"puadai","keyword":"puadai"},{"uri":"puah","keyword":"puah"},{"uri":"puak","keyword":"puak"},{"uri":"puaka","keyword":"puaka"},{"uri":"pual","keyword":"pual"},{"uri":"pualam","keyword":"pualam"},{"uri":"puan","keyword":"puan"},{"uri":"puas","keyword":"puas"},{"uri":"puasa","keyword":"puasa"},{"uri":"puatang","keyword":"puatang"},{"uri":"pub","keyword":"pub"},{"uri":"puber","keyword":"puber"},{"uri":"pubertas","keyword":"pubertas"},{"uri":"pubesens","keyword":"pubesens"},{"uri":"publik","keyword":"publik"},{"uri":"publikasi","keyword":"publikasi"},{"uri":"publisir","keyword":"publisir"},{"uri":"publisis","keyword":"publisis"},{"uri":"publisistik","keyword":"publisistik"},{"uri":"publisitas","keyword":"publisitas"},{"uri":"pucang","keyword":"pucang"},{"uri":"pucat","keyword":"pucat"},{"uri":"pucik","keyword":"pucik"},{"uri":"pucuk","keyword":"pucuk"},{"uri":"pucung","keyword":"pucung"}]}
