{"arti":["<b>re&#xB7;sor</b> /r&#xE9;sor/ <i>n</i> <b>1</b> daerah kecil; <b>2</b> daerah kuasa: <i>ia menjabat komandan -- kepolisian;</i> <b>3</b> lingkungan kerja: <i>tenaga kerja yg terdaftar pd kantor -- adalah tenaga kerja yg belum dapat disalurkan</i>"],"similar":[{"uri":"resorpsi","keyword":"resorpsi"},{"uri":"resorsinol","keyword":"resorsinol"},{"uri":"resolusi","keyword":"resolusi"},{"uri":"resonan","keyword":"resonan"},{"uri":"resonansi","keyword":"resonansi"},{"uri":"resonator","keyword":"resonator"},{"uri":"resosialisasi","keyword":"resosialisasi"},{"uri":"resa","keyword":"resa"},{"uri":"resah","keyword":"resah"},{"uri":"resak","keyword":"resak"},{"uri":"resam","keyword":"resam"},{"uri":"resan","keyword":"resan"},{"uri":"resap","keyword":"resap"},{"uri":"resbang","keyword":"resbang"},{"uri":"resek","keyword":"resek"},{"uri":"resensi","keyword":"resensi"},{"uri":"resensor","keyword":"resensor"},{"uri":"resep","keyword":"resep"},{"uri":"resepsi","keyword":"resepsi"},{"uri":"resepsionis","keyword":"resepsionis"},{"uri":"reseptif","keyword":"reseptif"},{"uri":"reseptor","keyword":"reseptor"},{"uri":"reserse","keyword":"reserse"},{"uri":"resersir","keyword":"resersir"},{"uri":"reservat","keyword":"reservat"},{"uri":"reserve","keyword":"reserve"},{"uri":"reservoir","keyword":"reservoir"},{"uri":"reses","keyword":"reses"},{"uri":"resesi","keyword":"resesi"},{"uri":"resi","keyword":"resi"}]}
