{"arti":["<b>Se&#xB7;nin</b> <i>n</i> hari ke-2 dl jangka waktu satu minggu;<br>--<b> Kamis</b> <i>ki</i> <b>1</b> sangat susah (tt hidup): <i>hidupnya -- Kamis;</i> <b>2</b> <i>ki</i> sesak; tersengal-sengal (tt napas): <i>napasnya -- Kamis</i>"],"similar":[{"uri":"seni","keyword":"seni"},{"uri":"senigai","keyword":"senigai"},{"uri":"senil","keyword":"senil"},{"uri":"senilitas","keyword":"senilitas"},{"uri":"seniman","keyword":"seniman"},{"uri":"senior","keyword":"senior"},{"uri":"senioritas","keyword":"senioritas"},{"uri":"seniwan","keyword":"seniwan"},{"uri":"seniwati","keyword":"seniwati"},{"uri":"sen","keyword":"sen"},{"uri":"sena","keyword":"sena"},{"uri":"senak","keyword":"senak"},{"uri":"senam","keyword":"senam"},{"uri":"senamaki","keyword":"senamaki"},{"uri":"senandika","keyword":"senandika"},{"uri":"senandung","keyword":"senandung"},{"uri":"senang","keyword":"senang"},{"uri":"senangin","keyword":"senangin"},{"uri":"senantan","keyword":"senantan"},{"uri":"senantiasa","keyword":"senantiasa"},{"uri":"senapan","keyword":"senapan"},{"uri":"senapati","keyword":"senapati"},{"uri":"senar","keyword":"senar"},{"uri":"senarai","keyword":"senarai"},{"uri":"senario","keyword":"senario"},{"uri":"senat","keyword":"senat"},{"uri":"senator","keyword":"senator"},{"uri":"senawan","keyword":"senawan"},{"uri":"senawar","keyword":"senawar"},{"uri":"senawat","keyword":"senawat"}]}
