{"arti":["<b>sya&#xB7;rat</b> <i>n</i> <b>1</b> janji (sbg tuntutan atau permintaan yg harus dipenuhi): <i>saya mau hadir dl rapat itu, dng -- saya tidak mau dipilih jadi pengurus;</i> <b>2</b> segala sesuatu yg perlu atau harus ada (sedia, dimiliki, dsb): <i>keamanan dl negeri adalah -- mutlak bagi pembangunan negara;</i> <b>3</b> segala sesuatu yg perlu untuk menyampaikan suatu maksud: <i>niat untuk belajar sangat besar, tetapi -- nya tidak mencukupi;</i> <b>4</b> ketentuan (peraturan, petunjuk) yg harus diindahkan dan dilakukan: <i>sbg umat Islam kita harus selalu patuh pd -- dan hukum Islam;</i> <b>5</b> biaya (barang-barang dsb) yg harus diberikan kpd guru pencak, dukun, dsb: --<i> apa saja yg harus dipenuhi jika berdukun kepadanya;<br></i><b>ber&#xB7;sya&#xB7;rat</b> <i>v</i> dng syarat (dl berbagai-bagai arti); memakai syarat: <i>perjanjian itu tidak -;<br></i><b>men&#xB7;sya&#xB7;rat&#xB7;kan</b> <i>v</i> menentukan sesuatu sbg syarat; menjadikan syarat;<br><b>per&#xB7;sya&#xB7;rat&#xB7;an</b> <i>n</i> hal-hal yg menjadi syarat;<br><b>- kerja</b> <i>Adm</i> persyaratan yg harus dipenuhi oleh seseorang agar dapat diterima sbg pegawai atau karyawan"],"similar":[{"uri":"syarab","keyword":"syarab"},{"uri":"syaraf","keyword":"syaraf"},{"uri":"syarah","keyword":"syarah"},{"uri":"syarak","keyword":"syarak"},{"uri":"syar","keyword":"syar"},{"uri":"syarbat","keyword":"syarbat"},{"uri":"syarekat","keyword":"syarekat"},{"uri":"syariah","keyword":"syariah"},{"uri":"syariat","keyword":"syariat"},{"uri":"syarif","keyword":"syarif"},{"uri":"syarifah","keyword":"syarifah"},{"uri":"syarik","keyword":"syarik"},{"uri":"syarikat","keyword":"syarikat"},{"uri":"syabah","keyword":"syabah"},{"uri":"Syaban","keyword":"Syaban"},{"uri":"syabas","keyword":"syabas"},{"uri":"syafaat","keyword":"syafaat"},{"uri":"syafakat","keyword":"syafakat"},{"uri":"Syafii","keyword":"Syafii"},{"uri":"syafkah","keyword":"syafkah"},{"uri":"syagar","keyword":"syagar"},{"uri":"syah","keyword":"syah"},{"uri":"syahada","keyword":"syahada"},{"uri":"syahadan","keyword":"syahadan"},{"uri":"syahadat","keyword":"syahadat"},{"uri":"syahadatain","keyword":"syahadatain"},{"uri":"syahbandar","keyword":"syahbandar"},{"uri":"syahda","keyword":"syahda"},{"uri":"syahdan","keyword":"syahdan"},{"uri":"syahdu","keyword":"syahdu"}]}
