{"arti":["<b><sup>1</sup>ta&#xB7;ni</b> <i>n</i> <b>1</b> mata pencaharian dl bentuk bercocok tanam; mata pencarian dl bentuk mengusahakan tanah dng tanam-menanam;<br><b>ber&#xB7;ta&#xB7;ni</b> <i>v</i> bercocok tanam; mengusahakan tanah dng tanam-menanam;<br><b>per&#xB7;ta&#xB7;ni&#xB7;an</b> <i>n</i> <b>1</b> perihal bertani (mengusahakan tanah dng tanam-menanam); <b>2</b> segala yg bertalian dng tanam-menanam (pengusahaan tanah dsb);<br>~<b> ekstraktif</b> pertanian yg pengusahaannya dng mengambil hasil dr alam dan tanah tanpa usaha menyuburkan kembali tanah dsb untuk keperluan pengambilan pd kemudian hari: ~<b> generatif</b> pertanian yg memerlukan usaha pembibitan, pengolahan, pemeliharaan, dsb (pd tanaman dan hewan); ~<b> huma</b> pertanian ladang; ~<b> kering</b> pertanian tanpa irigasi di daerah yg curah hujannya terbatas; ~<b> komersial</b> pertanian yg bertujuan memenuhi keperluan perdagangan: ~<b> ladang</b> corak usaha tani primitif dng menebang pohon-pohonan untuk dibakar sehingga tanah dapat ditanami; ~<b> menetap</b> pertanian yg diusahakan secara menetap dng menggarap bidang tanah yg sama dr tahun ke tahun; ~<b> monokultur</b> usaha pertanian untuk satu jenis tanaman pd sebidang lahan; ~<b> multikultur</b> usaha pertanian untuk beberapa jenis tanaman pd sebidang lahan;<br><b>pe&#xB7;ta&#xB7;ni</b> <i>n</i> orang yg pekerjaannya bercocok tanam;<br>~<b> berdasi</b> <i>cak</i> pemilik sawah (kebun dsb) yg tidak pernah mengerjakan sendiri tanahnya; ~<b><i> </i>gurem</b> <i>ki</i> petani kecil (biasa memiliki lahan kurang dr 0,25 ha); ~<b> monokultur</b> petani yg hanya menanam satu jenis tanaman; ~<b> penggarap</b> petani yg menggarap tanah orang lain dng sistem bagi hasil; ~<b> tambak</b> orang yg mengusahakan tambak; petambak<br><b>2ta&#xB7;ni</b> <i>ark n</i> tali-temali di perahu untuk meneguhkan tiang; temberang","<b><sup>3</sup>ta&#xB7;ni</b> <i>kl</i> <i>n</i> pintu gerbang sebelah luar istana"],"similar":[{"uri":"tania","keyword":"tania"},{"uri":"tanin","keyword":"tanin"},{"uri":"tan","keyword":"tan"},{"uri":"tan-","keyword":"tan-"},{"uri":"tanah","keyword":"tanah"},{"uri":"tanai","keyword":"tanai"},{"uri":"tanak","keyword":"tanak"},{"uri":"tanam","keyword":"tanam"},{"uri":"tanang","keyword":"tanang"},{"uri":"tanau","keyword":"tanau"},{"uri":"tanazul","keyword":"tanazul"},{"uri":"tanbiat","keyword":"tanbiat"},{"uri":"tanbihat","keyword":"tanbihat"},{"uri":"tancang","keyword":"tancang"},{"uri":"tancap","keyword":"tancap"},{"uri":"tanda","keyword":"tanda"},{"uri":"tanda+tangan","keyword":"tanda tangan"},{"uri":"tandak","keyword":"tandak"},{"uri":"tandan","keyword":"tandan"},{"uri":"tandang","keyword":"tandang"},{"uri":"tandas","keyword":"tandas"},{"uri":"tandem","keyword":"tandem"},{"uri":"tandik","keyword":"tandik"},{"uri":"tandikat","keyword":"tandikat"},{"uri":"tandil","keyword":"tandil"},{"uri":"tanding","keyword":"tanding"},{"uri":"tandon","keyword":"tandon"},{"uri":"tandu","keyword":"tandu"},{"uri":"tanduk","keyword":"tanduk"},{"uri":"tandun","keyword":"tandun"}]}
