{"arti":["<b><sup>1</sup>te&#xB7;beng</b> /t&#xE9;b&#xE9;ng/ <i>n</i> pendinding (dr kajang, layar, tikar, dsb) untuk menolak panas matahari: --<i> jendela; -- pintu;<br></i><b>me&#xB7;ne&#xB7;beng</b> <i>v</i> <b>1</b> memampangkan, merentangkan (kajang, layar, dsb) untuk pendinding; <b>2</b> membeberkan (membentangkan kain dsb) untuk diperlihatkan; <b>3</b> <i>ki</i> menutup-nutupi kejahatan (kesalahan);<br>~<b> dada</b> <i>kl</i> memampangkan dada;<br><b>me&#xB7;ne&#xB7;beng&#xB7;kan</b> <i>v</i> menebeng","<b><sup>2</sup>te&#xB7;beng</b> /t&#xE9;b&#xE9;ng/ <i>Jk v,</i> <b>me&#xB7;ne&#xB7;beng</b> <i>v</i> menumpang (makan, merokok, membaca surat kabar, dsb) tanpa membayar: <i>ia membawa mobil dan kami ikut ~ keliling kota</i>","<b><sup>3</sup>te&#xB7;beng</b> /t&#xE9;b&#xE9;ng/ <i>v,</i> <b>ber&#xB7;te&#xB7;beng</b> <i>v</i> bergunting rambut: <i>sebulan sekali dia ~ di salon dekat rumahnya</i>"],"similar":[{"uri":"/tebera","keyword":"tebera"},{"uri":"/teberau","keyword":"teberau"},{"uri":"/tebah","keyword":"tebah"},{"uri":"/tebak","keyword":"tebak"},{"uri":"/tebakang","keyword":"tebakang"},{"uri":"/tebal","keyword":"tebal"},{"uri":"/teban","keyword":"teban"},{"uri":"/tebang","keyword":"tebang"},{"uri":"/tebar","keyword":"tebar"},{"uri":"/tebas","keyword":"tebas"},{"uri":"/tebat","keyword":"tebat"},{"uri":"/tebing","keyword":"tebing"},{"uri":"/tebok","keyword":"tebok"},{"uri":"/tebon","keyword":"tebon"},{"uri":"/tebu","keyword":"tebu"},{"uri":"/tebuan","keyword":"tebuan"},{"uri":"/tebuhar","keyword":"tebuhar"},{"uri":"/tebuk","keyword":"tebuk"},{"uri":"/tebung","keyword":"tebung"},{"uri":"/tebus","keyword":"tebus"},{"uri":"/te","keyword":"te"},{"uri":"/tean","keyword":"tean"},{"uri":"/teater","keyword":"teater"},{"uri":"/teatris","keyword":"teatris"},{"uri":"/tedak","keyword":"tedak"},{"uri":"/tedarus","keyword":"tedarus"},{"uri":"/tedas","keyword":"tedas"},{"uri":"/tedeng","keyword":"tedeng"},{"uri":"/tedong","keyword":"tedong"},{"uri":"/teduh","keyword":"teduh"}]}
