{"arti":["<b><sup>1</sup>te&#xB7;lut</b> <i>v,</i> <b>ber&#xB7;te&#xB7;lut</b> <i>v</i> berlutut: <i>maka ~ lah ia di tanah sambil menangis</i>","<b><sup>2</sup>te&#xB7;lut</b> <i>a</i> mempan (tt senjata); terlut; telap: <i>tidak --</i>","<b><sup>3</sup>te&#xB7;lut</b> <i>v,</i> <b>me&#xB7;ne&#xB7;lut</b> <i>v</i> memotong cabang atau batang (singkong, anggur, dsb) untuk ditanamkan; setek"],"similar":[{"uri":"telutuh","keyword":"telutuh"},{"uri":"telutur","keyword":"telutur"},{"uri":"telutut","keyword":"telutut"},{"uri":"teluh","keyword":"teluh"},{"uri":"teluk","keyword":"teluk"},{"uri":"teluki","keyword":"teluki"},{"uri":"telukup","keyword":"telukup"},{"uri":"telungkup","keyword":"telungkup"},{"uri":"telunjuk","keyword":"telunjuk"},{"uri":"telur","keyword":"telur"},{"uri":"telurit","keyword":"telurit"},{"uri":"telus","keyword":"telus"},{"uri":"telusuk","keyword":"telusuk"},{"uri":"telusur","keyword":"telusur"},{"uri":"tel","keyword":"tel"},{"uri":"tela","keyword":"tela"},{"uri":"telaah","keyword":"telaah"},{"uri":"telabang","keyword":"telabang"},{"uri":"telabat","keyword":"telabat"},{"uri":"telacak","keyword":"telacak"},{"uri":"teladan","keyword":"teladan"},{"uri":"teladas","keyword":"teladas"},{"uri":"telaga","keyword":"telaga"},{"uri":"telah","keyword":"telah"},{"uri":"telajak","keyword":"telajak"},{"uri":"telak","keyword":"telak"},{"uri":"telakan","keyword":"telakan"},{"uri":"telakup","keyword":"telakup"},{"uri":"telampung","keyword":"telampung"},{"uri":"telan","keyword":"telan"}]}
