{"arti":["<b>te&#xB7;na&#xB7;ga ker&#xB7;ja</b> <i>n</i> <b>1</b> orang yg bekerja atau mengerjakan sesuatu; pekerja, pegawai, dsb: <i>proyek itu masih memerlukan ratusan --;</i> <b>2</b> orang yg mampu melakukan pekerjaan, baik di dalam maupun di luar hubungan kerja;<br><b>ke&#xB7;te&#xB7;na&#xB7;ga&#xB7;ker&#xB7;ja&#xB7;an</b> <i>n</i> hal tenaga kerja"],"similar":[{"uri":"tenaga","keyword":"tenaga"},{"uri":"tenaga+nuklir","keyword":"tenaga nuklir"},{"uri":"tenahak","keyword":"tenahak"},{"uri":"tenak","keyword":"tenak"},{"uri":"tenam","keyword":"tenam"},{"uri":"tenang","keyword":"tenang"},{"uri":"tenar","keyword":"tenar"},{"uri":"tenat","keyword":"tenat"},{"uri":"tenda","keyword":"tenda"},{"uri":"tendang","keyword":"tendang"},{"uri":"tendas","keyword":"tendas"},{"uri":"tendensi","keyword":"tendensi"},{"uri":"tendensius","keyword":"tendensius"},{"uri":"tender","keyword":"tender"},{"uri":"tendinitis","keyword":"tendinitis"},{"uri":"tendo","keyword":"tendo"},{"uri":"tendon","keyword":"tendon"},{"uri":"tener","keyword":"tener"},{"uri":"teng","keyword":"teng"},{"uri":"tengadah","keyword":"tengadah"},{"uri":"tengah","keyword":"tengah"},{"uri":"tengak","keyword":"tengak"},{"uri":"tengalan","keyword":"tengalan"},{"uri":"tengar","keyword":"tengar"},{"uri":"tengara","keyword":"tengara"},{"uri":"tengas","keyword":"tengas"},{"uri":"tenggadai","keyword":"tenggadai"},{"uri":"tenggak","keyword":"tenggak"},{"uri":"tenggala","keyword":"tenggala"},{"uri":"tenggalung","keyword":"tenggalung"}]}
