{"arti":["<b>te&#xB7;o&#xB7;re&#xB7;ti&#xB7;kus</b> /t&#xE9;or&#xE9;tikus/ <i>n</i> ahli dl hal teori suatu ilmu: <i>ia bukan seorang -- melainkan ahli ilmu psikologi terapan</i>"],"similar":[{"uri":"/teoretis","keyword":"teoretis"},{"uri":"/teori","keyword":"teori"},{"uri":"/teorisasi","keyword":"teorisasi"},{"uri":"/teodolit","keyword":"teodolit"},{"uri":"/teokrasi","keyword":"teokrasi"},{"uri":"/teokratis","keyword":"teokratis"},{"uri":"/teolog","keyword":"teolog"},{"uri":"/teologi","keyword":"teologi"},{"uri":"/teologis","keyword":"teologis"},{"uri":"/teosofi","keyword":"teosofi"},{"uri":"/teosofis","keyword":"teosofis"},{"uri":"/te","keyword":"te"},{"uri":"/tean","keyword":"tean"},{"uri":"/teater","keyword":"teater"},{"uri":"/teatris","keyword":"teatris"},{"uri":"/tebah","keyword":"tebah"},{"uri":"/tebak","keyword":"tebak"},{"uri":"/tebakang","keyword":"tebakang"},{"uri":"/tebal","keyword":"tebal"},{"uri":"/teban","keyword":"teban"},{"uri":"/tebang","keyword":"tebang"},{"uri":"/tebar","keyword":"tebar"},{"uri":"/tebas","keyword":"tebas"},{"uri":"/tebat","keyword":"tebat"},{"uri":"/tebeng","keyword":"tebeng"},{"uri":"/tebera","keyword":"tebera"},{"uri":"/teberau","keyword":"teberau"},{"uri":"/tebing","keyword":"tebing"},{"uri":"/tebok","keyword":"tebok"},{"uri":"/tebon","keyword":"tebon"}]}
